potatoscript/potatoCSV.py
potatoCSV-1.0.0.dist-info/METADATA
potatoCSV-1.0.0.dist-info/WHEEL
potatoCSV-1.0.0.dist-info/top_level.txt
potatoCSV-1.0.0.dist-info/RECORD
