Metadata-Version: 2.1
Name: potatoCSV
Version: 1.0.0
Summary: A simple library for csv file and split the value
Author: ks lim
Author-email: kianseng.lim@sony.com
